torchmd/__init__.py
torchmd/_version.py
torchmd/forces.py
torchmd/integrator.py
torchmd/minimizers.py
torchmd/mycalc.py
torchmd/neighbourlist.py
torchmd/npzmol.py
torchmd/parameters.py
torchmd/run.py
torchmd/systems.py
torchmd/utils.py
torchmd/wrapper.py
torchmd/forcefields/__init__.py
torchmd/forcefields/ff_parmed.py
torchmd/forcefields/ff_yaml.py
torchmd/forcefields/forcefield.py
torchmd-1.0.4.dist-info/LICENSE.md
torchmd-1.0.4.dist-info/METADATA
torchmd-1.0.4.dist-info/WHEEL
torchmd-1.0.4.dist-info/top_level.txt
torchmd-1.0.4.dist-info/RECORD
