Metadata-Version: 2.2
Name: torchmd
Version: 1.0.4
Summary: TorchMD. Molecular dynamics with pytorch
Author-email: Acellera <info@acellera.com>
License: Copyright (c) 2020 Acellera
Project-URL: homepage, https://github.com/torchmd/torchmd/
Project-URL: repository, https://github.com/torchmd/torchmd/
Classifier: Operating System :: POSIX :: Linux
Classifier: Programming Language :: Python :: 3
Classifier: License :: OSI Approved :: MIT License
License-File: LICENSE.md
Requires-Dist: pyyaml
Requires-Dist: tqdm
Requires-Dist: moleculekit
Requires-Dist: pandas
Requires-Dist: networkx
Requires-Dist: scipy
